build/lib/vppapigen/__init__.py
build/lib/vppapigen/vppapigen.py
build/lib/vppapigen/emitters/__init__.py
build/lib/vppapigen/emitters/vppapigen_c.py
build/lib/vppapigen/emitters/vppapigen_crc.py
build/lib/vppapigen/emitters/vppapigen_json.py
vppapigen/__init__.py
vppapigen/generate_json.py
vppapigen/vppapigen.py
vppapigen/vppapigen_c.py
vppapigen/vppapigen_crc.py
vppapigen/vppapigen_json.py
vppapigen/emitters/__init__.py
vppapigen/emitters/vppapigen_c.py
vppapigen/emitters/vppapigen_crc.py
vppapigen/emitters/vppapigen_json.py
vppapigen-0.0.1.dist-info/METADATA
vppapigen-0.0.1.dist-info/WHEEL
vppapigen-0.0.1.dist-info/entry_points.txt
vppapigen-0.0.1.dist-info/top_level.txt
vppapigen-0.0.1.dist-info/RECORD
